wminhyuk_eda-0.4.2.dist-info/METADATA
wminhyuk_eda-0.4.2.dist-info/WHEEL
wminhyuk_eda-0.4.2.dist-info/entry_points.txt
wminhyuk_eda/__init__.py
wminhyuk_eda/cli.py
wminhyuk_eda-0.4.2.dist-info/RECORD
